tests/__init__.py
tests/utils_test.py
utils4py/Arial.ttf
utils4py/__init__.py
utils4py/blueprint.py
utils4py/captcha.py
utils4py/flask_utils.py
utils4py/utils.py
utils4py-0.0.40.dist-info/METADATA
utils4py-0.0.40.dist-info/WHEEL
utils4py-0.0.40.dist-info/top_level.txt
utils4py-0.0.40.dist-info/RECORD
